{
  "id": "galaxy",
  "type": "theme",
  "name": "Galaxy",
  "version": "1.0.0",
  "description": "A cosmic galaxy theme with harmonious nebula effects",
  "active": true,
  "data": {
    "colors": {
      "background": "#0a0a2a",
      "surface": "#1a1a4a",
      "primary": "#7b68ee",
      "primaryLight": "#9f8fff",
      "primaryDark": "#483d8b",
      "accent": "#ff4500",
      "textPrimary": "#00ff00",
      "textSecondary": "#ffff00",
      "border": "#2a2a6a"
    },
    "effects": {
      "knobGlow": true,
      "knobGlowIntensity": 1.8,
      "touchGlow": true,
      "touchGlowIntensity": 1.6,
      "textGlow": true,
      "textGlowIntensity": 1.4,
      "gradientBackground": true,
      "gradientAngle": 135,
      "animatedBackground": true,
      "animationDuration": 20,
      "starEffect": true,
      "starCount": 50,
      "starColor": "rgba(255, 255, 255, 0.5)"
    }
  }
} 